{"metadata": {"dbt_schema_version": "https://schemas.getdbt.com/dbt/sources/v3.json", "dbt_version": "1.8.8", "generated_at": "2024-12-10T13:01:42.807275Z", "invocation_id": "045f8c39-7e48-4820-bdbb-28c7d1de45db", "env": {}}, "results": [{"unique_id": "source.dbtlearn.airbnb.reviews", "max_loaded_at": "2024-12-08T21:25:36.705000+00:00", "snapshotted_at": "2024-12-10T13:01:41.583000+00:00", "max_loaded_at_time_ago_in_s": 142564.878, "status": "error", "criteria": {"warn_after": {"count": 1, "period": "hour"}, "error_after": {"count": 24, "period": "hour"}, "filter": null}, "adapter_response": {"_message": "SUCCESS 1", "code": "SUCCESS", "rows_affected": 1, "query_id": "01b8efed-0000-3ce7-0000-07a50001e0ba"}, "timing": [{"name": "compile", "started_at": "2024-12-10T13:01:40.290162Z", "completed_at": "2024-12-10T13:01:40.290170Z"}, {"name": "execute", "started_at": "2024-12-10T13:01:40.290562Z", "completed_at": "2024-12-10T13:01:42.800927Z"}], "thread_id": "Thread-1 (worker)", "execution_time": 2.5119469165802}], "elapsed_time": 5.774886846542358}